nlp_defaults/__init__.py
nlp_defaults/defaults.py
nlp_defaults-0.0.0.dist-info/METADATA
nlp_defaults-0.0.0.dist-info/WHEEL
nlp_defaults-0.0.0.dist-info/top_level.txt
nlp_defaults-0.0.0.dist-info/RECORD
